{
  "cantos": [
    {
      "number": 1,
      "chapters": []
    },
    {
      "number": 2,
      "chapters": []
    },
    {
      "number": 3,
      "chapters": []
    },
    {
      "number": 4,
      "chapters": []
    },
    {
      "number": 5,
      "chapters": []
    },
    {
      "number": 6,
      "chapters": []
    },
    {
      "number": 7,
      "chapters": []
    },
    {
      "number": 8,
      "chapters": []
    },
    {
      "number": 9,
      "chapters": []
    },
    {
      "number": 10,
      "chapters": []
    },
    {
      "number": 11,
      "chapters": []
    },
    {
      "number": 12,
      "chapters": []
    },
    {
      "number": 1,
      "chapters": []
    },
    {
      "number": 2,
      "chapters": []
    },
    {
      "number": 3,
      "chapters": []
    },
    {
      "number": 4,
      "chapters": []
    },
    {
      "number": 5,
      "chapters": []
    },
    {
      "number": 6,
      "chapters": []
    },
    {
      "number": 7,
      "chapters": []
    },
    {
      "number": 8,
      "chapters": []
    },
    {
      "number": 9,
      "chapters": []
    },
    {
      "number": 10,
      "chapters": []
    },
    {
      "number": 11,
      "chapters": []
    },
    {
      "number": 12,
      "chapters": []
    }
  ]
}